{"filename":"Menu","ext":".json","history":false,"dir":"root","write":"all","lunch":{"title":"Lunch","filename":"lunch","dir":"menu","pdf":"http://localhost/tapz/data//menu/ots-lunch.pdf","images":[{"url":"http://localhost/tapz/data/menu/ots-LunchPage1.jpeg","path":"/menu/ots-LunchPage1.jpeg","alt":"Oliver Twist Stockholm Lunch Page-1"}],"seo":"http://localhost/tapz/data/menu/lunch.html","snap":null},"food":{"title":"A la carte","filename":"food","dir":"menu","pdf":"http://localhost/tapz/data//menu/ots-food.pdf","images":[{"url":"http://localhost/tapz/data/menu/ots-AlacartePage1.jpeg","path":"/menu/ots-AlacartePage1.jpeg","alt":"Oliver Twist Stockholm A la carte Page-1"}],"seo":"http://localhost/tapz/data/menu/food.html","snap":null},"drinks":{"title":"Drinks","filename":"drinks","dir":"menu","pdf":"http://localhost/tapz/data//menu/ots-drinks.pdf","images":[{"url":"http://localhost/tapz/data/menu/ots-DrinksPage1.jpeg","path":"/menu/ots-DrinksPage1.jpeg","alt":"Oliver Twist Stockholm Drinks Page-1"},{"url":"http://localhost/tapz/data/menu/ots-DrinksPage2.jpeg","path":"/menu/ots-DrinksPage2.jpeg","alt":"Oliver Twist Stockholm Drinks Page-2"},{"url":"http://localhost/tapz/data/menu/ots-DrinksPage3.jpeg","path":"/menu/ots-DrinksPage3.jpeg","alt":"Oliver Twist Stockholm Drinks Page-3"},{"url":"http://localhost/tapz/data/menu/ots-DrinksPage4.jpeg","path":"/menu/ots-DrinksPage4.jpeg","alt":"Oliver Twist Stockholm Drinks Page-4"},{"url":"http://localhost/tapz/data/menu/ots-DrinksPage5.jpeg","path":"/menu/ots-DrinksPage5.jpeg","alt":"Oliver Twist Stockholm Drinks Page-5"},{"url":"http://localhost/tapz/data/menu/ots-DrinksPage6.jpeg","path":"/menu/ots-DrinksPage6.jpeg","alt":"Oliver Twist Stockholm Drinks Page-6"},{"url":"http://localhost/tapz/data/menu/ots-DrinksPage7.jpeg","path":"/menu/ots-DrinksPage7.jpeg","alt":"Oliver Twist Stockholm Drinks Page-7"},{"url":"http://localhost/tapz/data/menu/ots-DrinksPage8.jpeg","path":"/menu/ots-DrinksPage8.jpeg","alt":"Oliver Twist Stockholm Drinks Page-8"},{"url":"http://localhost/tapz/data/menu/ots-DrinksPage9.jpeg","path":"/menu/ots-DrinksPage9.jpeg","alt":"Oliver Twist Stockholm Drinks Page-9"},{"url":"http://localhost/tapz/data/menu/ots-DrinksPage10.jpeg","path":"/menu/ots-DrinksPage10.jpeg","alt":"Oliver Twist Stockholm Drinks Page-10"},{"url":"http://localhost/tapz/data/menu/ots-DrinksPage11.jpeg","path":"/menu/ots-DrinksPage11.jpeg","alt":"Oliver Twist Stockholm Drinks Page-11"}],"seo":"http://localhost/tapz/data/menu/drinks.html","snap":null}}